README.rst
setup.py
dbdiff/__init__.py
dbdiff/apps.py
dbdiff/exceptions.py
dbdiff/fixture.py
dbdiff/plugin.py
dbdiff/sequence.py
dbdiff/test.py
dbdiff/utils.py
dbdiff/serializers/__init__.py
dbdiff/serializers/base.py
dbdiff/serializers/json.py
dbdiff/tests/__init__.py
dbdiff/tests/test_compare.py
dbdiff/tests/test_decimal.py
dbdiff/tests/test_fixture.py
dbdiff/tests/test_mixin.py
dbdiff/tests/test_plugin.py
dbdiff/tests/test_utils.py
dbdiff/tests/decimal_test/__init__.py
dbdiff/tests/decimal_test/models.py
dbdiff/tests/decimal_test/migrations/0001_initial.py
dbdiff/tests/decimal_test/migrations/0002_auto_20160102_0914.py
dbdiff/tests/decimal_test/migrations/__init__.py
dbdiff/tests/inheritance/__init__.py
dbdiff/tests/inheritance/models.py
dbdiff/tests/nonintpk/__init__.py
dbdiff/tests/nonintpk/models.py
dbdiff/tests/project/__init__.py
dbdiff/tests/project/settings.py
dbdiff/tests/project/settings_mysql.py
dbdiff/tests/project/settings_postgresql.py
dbdiff/tests/project/settings_sqlite.py
dbdiff/tests/project/urls.py
django_dbdiff.egg-info/PKG-INFO
django_dbdiff.egg-info/SOURCES.txt
django_dbdiff.egg-info/dependency_links.txt
django_dbdiff.egg-info/entry_points.txt
django_dbdiff.egg-info/requires.txt
django_dbdiff.egg-info/top_level.txt